specrec/__init__.py
specrec/interfaces.py
specrec/object_factory.py
specrec_python-0.1.1.dist-info/licenses/LICENSE.md
specrec_python-0.1.1.dist-info/METADATA
specrec_python-0.1.1.dist-info/WHEEL
specrec_python-0.1.1.dist-info/top_level.txt
specrec_python-0.1.1.dist-info/RECORD
