Metadata-Version: 2.4
Name: specrec-python
Version: 0.1.1
Summary: SpecRec ObjectFactory dependency injection for Python
Author-email: Ivett Ördög <contact@ivettordog.com>
License: # PolyForm Noncommercial License 1.0.0
Project-URL: Homepage, https://github.com/anthropics/specrec
Project-URL: Repository, https://github.com/anthropics/specrec
Project-URL: Documentation, https://docs.specrec.com
Classifier: Development Status :: 3 - Alpha
Classifier: Intended Audience :: Developers
Classifier: Programming Language :: Python :: 3
Classifier: Programming Language :: Python :: 3.8
Classifier: Programming Language :: Python :: 3.9
Classifier: Programming Language :: Python :: 3.10
Classifier: Programming Language :: Python :: 3.11
Classifier: Programming Language :: Python :: 3.12
Requires-Python: >=3.8
License-File: LICENSE.md
Requires-Dist: typing-extensions>=4.0.0; python_version < "3.10"
Provides-Extra: test
Requires-Dist: pytest>=7.0.0; extra == "test"
Requires-Dist: pytest-cov>=4.0.0; extra == "test"
Provides-Extra: dev
Requires-Dist: mypy>=1.0.0; extra == "dev"
Requires-Dist: black>=22.0.0; extra == "dev"
Requires-Dist: isort>=5.0.0; extra == "dev"
Requires-Dist: pytest>=7.0.0; extra == "dev"
Requires-Dist: pytest-cov>=4.0.0; extra == "dev"
Dynamic: license-file
